Metadata-Version: 2.1
Name: sparktool
Version: 2.0.4
Summary: sparktool for hccn
Home-page: https://github.com/renyumm
Author: ryanren
Author-email: strrenyumm@gmail.com
License: UNKNOWN
Platform: UNKNOWN
Classifier: Programming Language :: Python :: 3
Classifier: License :: OSI Approved :: MIT License
Classifier: Operating System :: OS Independent
